compiletools/README.cleanup-remote-locks.rst
compiletools/README.create-documentation.rst
compiletools/README.ct-build-dynamic-library.rst
compiletools/README.ct-build-static-library.rst
compiletools/README.ct-build.rst
compiletools/README.ct-cake.rst
compiletools/README.ct-cleanup-locks.rst
compiletools/README.ct-commandline.rst
compiletools/README.ct-compilation-database.rst
compiletools/README.ct-config.rst
compiletools/README.ct-cppdeps.rst
compiletools/README.ct-create-makefile.rst
compiletools/README.ct-doc.rst
compiletools/README.ct-filelist.rst
compiletools/README.ct-findtargets.rst
compiletools/README.ct-git-sha-report.rst
compiletools/README.ct-gitroot.rst
compiletools/README.ct-headertree.rst
compiletools/README.ct-jobs.rst
compiletools/README.ct-list-variants.rst
compiletools/README.ct-lock-helper.rst
compiletools/README.ct-magicflags.rst
compiletools/README.ct-release.rst
compiletools/README.ct-watch-build.rst
compiletools/README.profile-ct-cake-worktree.rst
compiletools/__init__.py
compiletools/apptools.py
compiletools/cake.py
compiletools/cleanup_locks.py
compiletools/cleanup_locks_main.py
compiletools/compilation_database.py
compiletools/compiler_macros.py
compiletools/config.py
compiletools/configutils.py
compiletools/conftest.py
compiletools/cppdeps.py
compiletools/ct.conf.d/blank.conf
compiletools/ct.conf.d/blank.release.conf
compiletools/ct.conf.d/clang.debug.conf
compiletools/ct.conf.d/clang.release.conf
compiletools/ct.conf.d/ct.conf
compiletools/ct.conf.d/gcc.debug.conf
compiletools/ct.conf.d/gcc.release.conf
compiletools/doc.py
compiletools/file_analyzer.py
compiletools/filelist.py
compiletools/filesystem_utils.py
compiletools/findtargets.py
compiletools/git_sha_report.py
compiletools/git_utils.py
compiletools/global_hash_registry.py
compiletools/headerdeps.py
compiletools/headertree.py
compiletools/hunter.py
compiletools/jobs.py
compiletools/listvariants.py
compiletools/lock_utils.py
compiletools/locking.py
compiletools/magicflags.py
compiletools-7.0.2.dist-info/WHEEL
compiletools-7.0.2.dist-info/entry_points.txt
compiletools-7.0.2.dist-info/METADATA
compiletools-7.0.2.dist-info/RECORD
