Metadata-Version: 2.4
Name: compiletools
Version: 7.0.2
Summary: Tools to make compiling C/C++ projects easy
Keywords: c++,make,development
Author: DrGeoff
Author-email: DrGeoff <drgeoffathome@gmail.com>
License-Expression: GPL-3.0-or-later
Classifier: Development Status :: 5 - Production/Stable
Classifier: Intended Audience :: Developers
Classifier: Topic :: Software Development :: Build Tools
Classifier: License :: OSI Approved :: GNU General Public License v3 or later (GPLv3+)
Classifier: Programming Language :: Python :: 3
Classifier: Programming Language :: Python :: 3.9
Classifier: Programming Language :: Python :: 3.10
Classifier: Programming Language :: Python :: 3.11
Classifier: Programming Language :: Python :: 3.12
Classifier: Programming Language :: Python :: 3.13
Requires-Dist: configargparse>=1.5.3
Requires-Dist: appdirs>=1.4.4
Requires-Dist: psutil>=5.9.0
Requires-Dist: rich>=12.0.0
Requires-Dist: rich-rst>=1.1.7
Requires-Dist: stringzilla>=3.0.0
Requires-Dist: bump-my-version>=0.26.0 ; extra == 'dev'
Requires-Dist: twine>=5.0.0 ; extra == 'dev'
Requires-Dist: pytest>=7.0.2 ; extra == 'dev'
Requires-Dist: pytest-xdist>=3.5 ; extra == 'dev'
Requires-Dist: ruff>=0.12.9 ; extra == 'dev'
Requires-Python: >=3.9
Project-URL: Download, https://github.com/DrGeoff/compiletools/archive/v{version}.tar.gz
Project-URL: Homepage, http://drgeoff.github.io/compiletools/
Provides-Extra: dev
